MANIFEST.in
README.rst
setup.py
aliyun_python_sdk_smarthosting.egg-info/PKG-INFO
aliyun_python_sdk_smarthosting.egg-info/SOURCES.txt
aliyun_python_sdk_smarthosting.egg-info/dependency_links.txt
aliyun_python_sdk_smarthosting.egg-info/requires.txt
aliyun_python_sdk_smarthosting.egg-info/top_level.txt
aliyunsdksmarthosting/__init__.py
aliyunsdksmarthosting/endpoint.py
aliyunsdksmarthosting/request/__init__.py
aliyunsdksmarthosting/request/v20200801/ListManagedHostsRequest.py
aliyunsdksmarthosting/request/v20200801/ListManagedPrivateSpacesRequest.py
aliyunsdksmarthosting/request/v20200801/ListManagedRacksRequest.py
aliyunsdksmarthosting/request/v20200801/UpdateManagedHostAttributesRequest.py
aliyunsdksmarthosting/request/v20200801/__init__.py